{
  "metadata": {"schemaVersion":"1.0","id":"case-02","estimatedTime":"16 min","urgency":"Emergency","status":"not-started","score":null,"chiefComplaint":"I have severe pain in my upper-right tooth, I feel feverish, weak, and sick, and it has gotten much worse.","title":"Upper-Right Odontogenic Abscess with Cellulitis and Systemic Infection"},
  "patient": {"name":"Marcus Lee","age":21,"sex":"Not specified"},
  "voicePreference": {"provider":"navigator","voiceId":"am_liam","speed":1.04},
  "assets": {"rest":"/patients/case-02/case-02-marcus-lee-v4.png","talking":"/patients/case-02/talking-v4.mp4","examinations":[
    {"id":"vital-signs","title":"Vital Signs (on arrival)","type":"vital-signs","findings":[{"label":"Temperature","value":"38.4°C (101.1°F)"},{"label":"Heart Rate","value":"108 bpm"},{"label":"Blood Pressure","value":"132/80 mmHg"},{"label":"Respiratory Rate","value":"18 breaths/min"},{"label":"Oxygen Saturation","value":"98% on room air"}]},
    {"id":"oral-examination","title":"Oral and Facial Examination","type":"clinical-findings","findings":[{"label":"Upper-right gingiva","value":"Erythematous, swollen, and tender"},{"label":"Involved upper-right molar","value":"Markedly tender to touch and percussion"},{"label":"Cheek","value":"Increasing right cheek swelling"},{"label":"Mouth opening","value":"Uncomfortable but possible"},{"label":"Voice and secretions","value":"Normal voice; no drooling"},{"label":"Airway and breathing","value":"No airway distress; non-labored breathing"},{"label":"Cardiovascular","value":"Mild tachycardia"},{"label":"Dentition","value":"Poor dentition with no recent dental care"}]},
    {"id":"laboratory-results","title":"Laboratory Results","type":"diagnostic-results","findings":[{"label":"WBC","value":"14.8 ×10⁹/L"},{"label":"Differential","value":"Neutrophil predominant leukocytosis"},{"label":"Lactate","value":"Normal"},{"label":"Basic metabolic panel","value":"Within normal limits"}]},
    {"id":"ct-face","title":"CT Face with IV Contrast","type":"diagnostic-results","findings":[{"label":"Dental source","value":"Periapical abscess of the upper-right molar"},{"label":"Associated finding","value":"Surrounding facial cellulitis"},{"label":"Deep spaces","value":"No deep-space involvement"}]},
    {"id":"examination-01","title":"Focused Dental Examination Image","image":"/patients/case-02/examination/examination-01-v2.png","description":"Focused upper-right dental examination image."}
  ]},
  "conversation": {"openingGreeting":"Hello... I feel really sick.","scripted":[
    {"id":"c2-greeting","intent":"greeting","triggers":["hello","hi","good morning","good afternoon"],"response":"Hello... I feel really sick.","requiredFactsCovered":[],"checklistItemId":"greeting"},
    {"id":"c2-chief","intent":"chief_complaint","triggers":["what brings you in","why are you here","chief complaint"],"response":"My upper-right tooth hurts badly, my cheek is swelling, and I feel feverish, weak, and sick.","requiredFactsCovered":["chief_complaint"],"checklistItemId":"chief-complaint"},
    {"id":"c2-duration","intent":"duration","triggers":["how long has this been going on","how many days","duration"],"response":"It has been getting worse for seven days.","requiredFactsCovered":["duration"],"checklistItemId":"duration"},
    {"id":"c2-location","intent":"location","triggers":["where is the pain","which tooth","what side"],"response":"It is the back tooth on the upper-right side.","requiredFactsCovered":["location"],"checklistItemId":"location"},
    {"id":"c2-current-pain","intent":"current_pain","triggers":["is the pain constant now","pain all the time","does the pain stop"],"response":"It is constant now, severe and throbbing, about eight out of ten.","requiredFactsCovered":["current_pain"],"checklistItemId":"pain-character"},
    {"id":"c2-historical-thermal","intent":"thermal_history","triggers":["did hot or cold bother it earlier","hot or cold","cold earlier"],"response":"Earlier in the week, hot and cold triggered it. Now it hurts constantly.","requiredFactsCovered":["thermal_history"],"checklistItemId":"thermal-sensitivity"},
    {"id":"c2-biting","intent":"biting_pain","triggers":["hurt to chew","chewing","biting","touch the tooth","tap the tooth"],"response":"Yes. Chewing hurts, and now I can barely touch the tooth.","requiredFactsCovered":["biting_pain"],"checklistItemId":"biting-pain"},
    {"id":"c2-swelling","intent":"facial_swelling","triggers":["cheek swelling","facial swelling","is your face swollen"],"response":"Yes. My right cheek has become more swollen over about the last day.","requiredFactsCovered":["swelling"],"checklistItemId":"swelling"},
    {"id":"c2-fever","intent":"fever","triggers":["have you had a fever","do you have a fever","fever"],"response":"Yes. I have felt feverish and hot.","requiredFactsCovered":["fever"],"checklistItemId":"systemic-symptoms"},
    {"id":"c2-temperature","intent":"temperature_checked","triggers":["checked your temperature","measure your temperature","thermometer","exact temperature"],"response":"I feel feverish, but I do not know my exact temperature.","requiredFactsCovered":["temperature_checked"],"checklistItemId":"systemic-symptoms"},
    {"id":"c2-chills","intent":"chills","triggers":["any chills","chills"],"response":"Yes, I have had chills.","requiredFactsCovered":["chills"],"checklistItemId":"systemic-symptoms"},
    {"id":"c2-systemic","intent":"systemic_illness","triggers":["feel weak or sick","weakness","fatigue","feel ill"],"response":"I feel weak, tired, and sick.","requiredFactsCovered":["systemic_illness"],"checklistItemId":"systemic-symptoms"},
    {"id":"c2-medication","intent":"medications","triggers":["what medication did you take","what medicine","ibuprofen","motrin","advil"],"response":"I take ibuprofen, 400 milligrams as needed, about every six hours.","requiredFactsCovered":["medications"],"checklistItemId":"medications"},
    {"id":"c2-allergy","intent":"allergies","triggers":["allergic to penicillin","medication allergies","allergies"],"response":"I have no known drug allergies, and I am not allergic to penicillin.","requiredFactsCovered":["allergies"],"checklistItemId":"allergies"},
    {"id":"c2-breathing","intent":"breathing","triggers":["trouble breathing","difficulty breathing","short of breath"],"response":"No, I am not having trouble breathing.","requiredFactsCovered":["airway_negative"],"checklistItemId":"airway"},
    {"id":"c2-liquids","intent":"swallowing_liquids","triggers":["swallow liquids","swallow water","drink liquids"],"response":"Yes, I can swallow liquids.","requiredFactsCovered":["airway_negative"],"checklistItemId":"airway"},
    {"id":"c2-voice","intent":"voice_change","triggers":["voice changed","voice change","muffled voice"],"response":"No, my voice has not changed.","requiredFactsCovered":["airway_negative"],"checklistItemId":"airway"},
    {"id":"c2-drooling","intent":"drooling","triggers":["are you drooling","drooling","saliva"],"response":"No, I am not drooling.","requiredFactsCovered":["airway_negative"],"checklistItemId":"airway"},
    {"id":"c2-mouth-opening","intent":"mouth_opening","triggers":["open your mouth","mouth opening","trismus"],"response":"I can open my mouth, but it is uncomfortable.","requiredFactsCovered":["mouth_opening"],"checklistItemId":"airway"},
    {"id":"c2-access","intent":"dental_access","triggers":["last saw a dentist","lost medicaid","dental care","insurance"],"response":"I have not seen a dentist since I lost Medicaid last year.","requiredFactsCovered":["access_barrier"],"checklistItemId":"dental-history"}
  ]},
  "patientChecklist":[
    {"id":"greeting","label":"Opened the encounter respectfully","triggers":["hello","hi","good morning","good afternoon"],"weight":1,"domain":"communication"},
    {"id":"chief-complaint","label":"Asked what brought the patient in","triggers":["what brings","why are you here","chief complaint"],"weight":1,"domain":"history"},
    {"id":"duration","label":"Asked about the seven-day progression","triggers":["how long","how many days","duration"],"weight":1,"domain":"history"},
    {"id":"location","label":"Asked which tooth and side hurts","triggers":["where","which tooth","what side"],"weight":1,"domain":"history"},
    {"id":"thermal-sensitivity","label":"Asked about earlier hot or cold provocation","triggers":["cold","hot","thermal"],"weight":1,"domain":"history"},
    {"id":"biting-pain","label":"Asked about chewing, touching, or percussion pain","triggers":["bite","chew","touch","tap","percussion"],"weight":1,"domain":"history"},
    {"id":"swelling","label":"Asked about facial swelling and progression","triggers":["swelling","swollen","cheek","face"],"weight":1,"domain":"history"},
    {"id":"medications","label":"Asked about ibuprofen or home medication use","triggers":["medication","medicine","ibuprofen","motrin","advil"],"weight":1,"domain":"history"},
    {"id":"allergies","label":"Asked about medication or penicillin allergy","triggers":["allerg","penicillin"],"weight":1,"domain":"history"},
    {"id":"airway","label":"Asked targeted breathing, swallowing, voice, drooling, or mouth-opening questions","triggers":["breathing","swallow","voice","drool","open your mouth"],"weight":1,"domain":"history","critical":true},
    {"id":"systemic-symptoms","label":"Asked about fever, chills, weakness, fatigue, or systemic illness","triggers":["fever","chills","weak","fatigue","feel sick"],"weight":1,"domain":"history"},
    {"id":"dental-history","label":"Asked about dental care and Medicaid access","triggers":["dentist","dental care","medicaid","insurance"],"weight":1,"domain":"history"},
    {"id":"pain-character","label":"Asked about current pain character and severity","triggers":["pain","constant","throbbing","severity","scale"],"weight":1,"domain":"history"},
    {"id":"examination-findings","label":"Reviewed available examination or diagnostic results","triggers":["examination","exam","results","labs","ct"],"weight":1,"domain":"examination"}
  ],
  "clinicalChecklist":[
    {"id":"clinical-1","label":"Characterizes earlier thermal symptoms and current constant chewing pain","weight":2,"domain":"history"},
    {"id":"clinical-2","label":"Elicits fever, chills, weakness, fatigue, swelling, and airway red flags","weight":3,"domain":"history","critical":true},
    {"id":"clinical-3","label":"Reviews structured oral, facial, vital-sign, laboratory, and CT findings","weight":2,"domain":"examination"},
    {"id":"clinical-4","label":"Reviews medication, antibiotics, allergies, and source-control needs","weight":2,"domain":"management"},
    {"id":"clinical-5","label":"Recognizes systemic odontogenic infection with cellulitis as an emergency","weight":3,"domain":"reasoning","critical":true}
  ],
  "supportingInfo": {
    "patientFacts":[
      {"id":"c2.duration","topic":"onset_duration","text":"The upper-right dental pain has worsened over seven days.","questionIntents":["duration"]},
      {"id":"c2.location","topic":"location","text":"The painful tooth is an upper-right back molar.","questionIntents":["location"]},
      {"id":"c2.current-pain","topic":"pain","text":"The pain is now constant, severe, throbbing, and 8/10.","questionIntents":["current_pain","pain"]},
      {"id":"c2.severity","topic":"pain","text":"The current pain is 8/10.","questionIntents":["pain_severity"]},
      {"id":"c2.thermal-history","topic":"pain","text":"Earlier in the illness, hot and cold triggered the pain; it has now become constant.","questionIntents":["thermal"]},
      {"id":"c2.biting","topic":"pain","text":"Chewing is painful, and the involved tooth is extremely painful to touch.","questionIntents":["biting"]},
      {"id":"c2.percussion","topic":"pain","text":"Tapping the upper-right back tooth causes marked pain.","questionIntents":["percussion"]},
      {"id":"c2.swelling","topic":"swelling","text":"The right cheek swelling has increased over approximately 24 hours.","questionIntents":["facial_swelling","swelling_progression"]},
      {"id":"c2.systemic-timeline","topic":"onset_duration","text":"Subjective fever, chills, fatigue, and increasing right-cheek swelling developed over approximately 24 hours.","questionIntents":["systemic_timeline"]},
      {"id":"c2.fever","topic":"medical_history","text":"The patient has felt feverish and hot.","questionIntents":["fever"]},
      {"id":"c2.temperature-unknown","topic":"medical_history","text":"The patient feels feverish but does not know an exact temperature.","questionIntents":["temperature_checked"]},
      {"id":"c2.chills","topic":"medical_history","text":"The patient has had chills.","questionIntents":["chills"]},
      {"id":"c2.weak","topic":"medical_history","text":"The patient feels weak, fatigued, and systemically ill.","questionIntents":["systemic_illness"]},
      {"id":"c2.lymph-nodes","topic":"medical_history","text":"The patient has enlarged lymph nodes but does not know an exact node location or size.","questionIntents":["lymph_nodes"]},
      {"id":"c2.healthy","topic":"medical_history","text":"General health is excellent; the patient has no known medical problems.","questionIntents":["medical_conditions"]},
      {"id":"c2.med","topic":"medications","text":"The patient takes ibuprofen 400 mg as needed, approximately every six hours.","questionIntents":["medications"],"canonicalFactIds":["c2.med","c2.med-cadence"]},
      {"id":"c2.ibuprofen","topic":"medications","text":"The patient has no contraindication to ibuprofen, Motrin, or Advil.","questionIntents":["ibuprofen_tolerance"]},
      {"id":"c2.opioid","topic":"medical_history","text":"The patient has no history of opioid or narcotic use, opioid misuse, or opioid abuse.","questionIntents":["opioid_history"]},
      {"id":"c2.nkda","topic":"allergies","text":"The patient has no known drug allergies and no penicillin allergy.","questionIntents":["allergies"]},
      {"id":"c2.breathing-negative","topic":"medical_history","text":"The patient has no difficulty breathing.","questionIntents":["breathing"],"canonicalFactIds":["c2.airway-negative"]},
      {"id":"c2.liquids-positive","topic":"medical_history","text":"The patient can swallow liquids.","questionIntents":["swallowing_liquids"],"canonicalFactIds":["c2.airway-negative"]},
      {"id":"c2.voice-negative","topic":"medical_history","text":"The patient's voice has not changed.","questionIntents":["voice_change"],"canonicalFactIds":["c2.airway-negative"]},
      {"id":"c2.drooling-negative","topic":"medical_history","text":"The patient is not drooling.","questionIntents":["drooling"],"canonicalFactIds":["c2.airway-negative"]},
      {"id":"c2.mouth-opening","topic":"medical_history","text":"The patient can open the mouth, although it is uncomfortable.","questionIntents":["mouth_opening"]},
      {"id":"c2.smoking","topic":"social_history","text":"The patient smokes approximately one-half pack of cigarettes per day.","questionIntents":["smoking"]},
      {"id":"c2.alcohol","topic":"social_history","text":"The patient uses alcohol rarely.","questionIntents":["alcohol_use"]},
      {"id":"c2.illicit-drugs","topic":"social_history","text":"The patient denies illicit-drug use.","questionIntents":["illicit_drug_use"]},
      {"id":"c2.access","topic":"dental_history","text":"The patient has not seen a dentist since losing Medicaid last year.","questionIntents":["dental_access"]},
      {"id":"c2.cavities-belief","topic":"dental_history","text":"The patient thinks the teeth are in poor condition and has seen spots that may be untreated cavities, without a dentist-confirmed diagnosis.","questionIntents":["dental_condition"]},
      {"id":"c2.prior-antibiotics-unknown","topic":"medications","text":"Prior antibiotic use for this problem is not established; the patient does not know or recall.","questionIntents":["prior_antibiotics"]},
      {"id":"c2.prior-root-canal-unknown","topic":"dental_history","text":"Prior root-canal treatment of the affected tooth is not established; the patient does not know or recall.","questionIntents":["prior_root_canal"]},
      {"id":"c2.prior-treatment-unknown","topic":"dental_history","text":"Other prior treatment of the affected tooth is not established; the patient does not recall having treatment done on that tooth.","questionIntents":["prior_treatment"]},
      {"id":"c2.painful-tooth-not-extracted","topic":"dental_history","text":"The currently painful upper-right molar is present, so that same tooth was not previously extracted.","questionIntents":["affected_tooth_extraction"]},
      {"id":"c2.other-extraction-unknown","topic":"dental_history","text":"Whether the patient has had another tooth extracted is not established; the patient does not know or recall.","questionIntents":["other_extraction"]},
      {"id":"c2.heart-rate-unknown","topic":"medical_history","text":"The patient does not know the exact measured heart rate unless told by the clinician.","questionIntents":["heart_rate_knowledge"]},
      {"id":"c2.sirs-unknown","topic":"medical_history","text":"The patient does not independently know whether clinical SIRS criteria are met.","questionIntents":["sirs_knowledge"]}
    ],
    "history":{"onset":"Pain started with hot and cold provocation and worsened throughout the week.","duration":"Seven days of worsening upper-right dental pain; cheek swelling and systemic symptoms increased over approximately 24 hours.","pain":"Initially hot/cold-provoked, now constant, severe, throbbing, and 8/10 with painful chewing and touch.","medications":"Ibuprofen 400 mg as needed approximately every six hours.","allergies":"No known drug allergies and no penicillin allergy.","medicalHistory":"Otherwise healthy; no known opioid-use history and no ibuprofen contraindication.","dentalHistory":"Poor dentition, untreated cavities, and no recent dental care since losing Medicaid.","socialHistory":"Smokes approximately half a pack per day; rare alcohol use; no illicit drug use."},
    "hpiFacts":["Seven days of worsening upper-right molar pain.","Earlier hot/cold provocation progressed to constant severe throbbing 8/10 pain.","Chewing and touching the tooth are very painful.","Increasing right cheek swelling over approximately 24 hours.","Fever, chills, fatigue, weakness, and systemic illness are present.","Mouth opening is uncomfortable but possible.","No drooling, voice change, dyspnea, or inability to swallow liquids."],
    "redFlags":["Fever and mild tachycardia","Neutrophilic leukocytosis","Facial cellulitis","Systemic illness","Risk of progression despite no current deep-space involvement"],
    "examinationFindings":["Upper-right gingival erythema, swelling, and tenderness","Marked upper-right molar touch and percussion tenderness","Increasing right cheek swelling","Uncomfortable but possible mouth opening","Normal voice, no drooling, and no airway distress","Temperature 38.4°C and heart rate 108","WBC 14.8 with neutrophil predominance","Normal lactate and BMP","CT-confirmed upper-right periapical abscess with facial cellulitis and no deep-space involvement"],
    "expectedQuestions":["How has the pain changed over seven days?","Did hot or cold trigger it earlier, and is it constant now?","Does chewing or touching the tooth hurt?","Have you had fever, chills, weakness, or fatigue?","Has the cheek swelling increased?","Can you breathe, swallow liquids, speak normally, and open your mouth?","What medication have you taken?","Do you have medication allergies, including penicillin or amoxicillin?","When did you last receive dental care?"],
    "diagnosis":"Upper-right odontogenic periapical abscess with facial cellulitis and systemic infection.",
    "differentialDiagnosis":["Facial cellulitis","Early deep-space infection","Osteomyelitis"],
    "managementExpectations":["Obtain CBC, BMP, lactate, and CT imaging.","Provide IV fluids, analgesia, and antipyretic treatment.","Start IV ampicillin-sulbactam or a faculty-approved equivalent.","Consult OMFS or an appropriate specialist and consider admission.","Arrange definitive dental treatment and source control within approximately 72 hours.","Explain that antibiotics alone do not definitively treat the tooth."],
    "requiredInvestigations":["CBC with differential","Basic metabolic panel","Lactate","CT face with IV contrast"],
    "treatmentExpectations":["IV fluids, analgesia, and antipyretic therapy.","IV ampicillin-sulbactam or faculty-approved equivalent.","Definitive dental source control within approximately 72 hours."],
    "referralExpectations":["OMFS or appropriate specialist consultation.","Consider hospital admission based on the emergency systemic-infection context."],
    "safetyNettingExpectations":["Do not treat antibiotics alone as definitive dental care.","Escalate for worsening swelling, swallowing difficulty, breathing difficulty, drooling, voice change, or other deep-space signs."],
    "learningObjectives":["Recognize cellulitis and systemic infection in an odontogenic abscess.","Interpret structured laboratory and CT results without conflating viewing with recognition.","Plan emergency IV treatment, consultation, possible admission, and timely source control."],
    "reportData":{"keyFindings":["Seven-day upper-right dental pain progression","Current constant severe throbbing 8/10 pain","Fever, chills, fatigue, weakness, and facial swelling","Temperature 38.4°C and heart rate 108","WBC 14.8 with neutrophilic leukocytosis","Normal lactate and BMP","CT-confirmed periapical abscess with facial cellulitis and no deep-space involvement"],"criticalMisses":["Failure to recognize systemic infection or emergency severity","Failure to assess airway and deep-space red flags","Failure to review laboratory or CT results","Routine discharge with oral antibiotics alone","Failure to arrange specialist input and definitive source control"],"idealSummary":"A 21-year-old with seven days of worsening upper-right molar pain that progressed from thermal provocation to constant severe throbbing 8/10 pain, with increasing cheek swelling, fever, chills, fatigue, weakness, temperature 38.4°C, heart rate 108, WBC 14.8 with neutrophilia, and CT-confirmed periapical abscess with facial cellulitis but no deep-space involvement, requiring emergency IV treatment, specialist consultation, possible admission, and definitive dental source control."},
    "evaluation":{"patientChecklistWeight":0.6,"clinicalChecklistWeight":0.4,"totalScore":"weightedAverage(patientChecklist, clinicalChecklist)"}
  }
}
